cranberry/__init__.py
cranberry/__main__.py
cranberry/cranberry.py
cranberry/crawler.py
cranberry/linter.py
cranberry/sensor.py
cranberry/songhandler.py
cranberry/uploader.py
cranberry/urlcreator.py
cranberry/urlhandler.py
cranberry/youtubeparser.py
cranberry-1.0.3.dist-info/DESCRIPTION.rst
cranberry-1.0.3.dist-info/METADATA
cranberry-1.0.3.dist-info/RECORD
cranberry-1.0.3.dist-info/WHEEL
cranberry-1.0.3.dist-info/dependency_links.txt
cranberry-1.0.3.dist-info/entry_points.txt
cranberry-1.0.3.dist-info/metadata.json
cranberry-1.0.3.dist-info/top_level.txt
