Metadata-Version: 2.0
Name: cranberry
Version: 1.0.3
Summary: An automated music downloading service
Home-page: https://github.com/danielschwabacher/cranberry
Author: Daniel Schwabacher
Author-email: danielschwabacher@gmail.com
License: BSD
Download-URL: https://github.com/danielschwabacher/cranberry/tarball/1.0.3
Keywords: automation music youtube-dl
Platform: UNKNOWN
Classifier: Development Status :: 3 - Alpha
Classifier: Intended Audience :: Developers
Classifier: Programming Language :: Python :: 3
Requires-Dist: sphinx
Requires-Dist: sphinx-rtd-theme
Requires-Dist: nose
Requires-Dist: coverage
Requires-Dist: pypi-publisher
Requires-Dist: youtube-dl
Requires-Dist: fake-useragent
